toolbox_core/__init__.py
toolbox_core/auth_methods.py
toolbox_core/client.py
toolbox_core/itransport.py
toolbox_core/protocol.py
toolbox_core/py.typed
toolbox_core/sync_client.py
toolbox_core/sync_tool.py
toolbox_core/tool.py
toolbox_core/toolbox_transport.py
toolbox_core/utils.py
toolbox_core/version.py
toolbox_core/mcp_transport/__init__.py
toolbox_core/mcp_transport/transport_base.py
toolbox_core/mcp_transport/v20241105/mcp.py
toolbox_core/mcp_transport/v20241105/types.py
toolbox_core/mcp_transport/v20250326/mcp.py
toolbox_core/mcp_transport/v20250326/types.py
toolbox_core/mcp_transport/v20250618/mcp.py
toolbox_core/mcp_transport/v20250618/types.py
toolbox_core-0.5.6.dist-info/METADATA
toolbox_core-0.5.6.dist-info/WHEEL
toolbox_core-0.5.6.dist-info/top_level.txt
toolbox_core-0.5.6.dist-info/RECORD
